qufilab/__init__.py
qufilab/__version__.py
qufilab/main.py
qufilab/models.cc
qufilab/common/time.cc
qufilab/indicators/__init__.py
qufilab/indicators/_momentum.cc
qufilab/indicators/_momentum.cpython-37m-darwin.so
qufilab/indicators/_stat.cc
qufilab/indicators/_stat.cpython-37m-darwin.so
qufilab/indicators/_trend.cc
qufilab/indicators/_trend.cpython-37m-darwin.so
qufilab/indicators/_volatility.cc
qufilab/indicators/_volatility.cpython-37m-darwin.so
qufilab/indicators/_volume.cc
qufilab/indicators/_volume.cpython-37m-darwin.so
qufilab/indicators/interface.py
qufilab/indicators/momentum.py
qufilab/indicators/stat.py
qufilab/indicators/trend.py
qufilab/indicators/volatility.py
qufilab/indicators/volume.py
qufilab/patterns/__init__.py
qufilab/patterns/_bullish.cc
qufilab/patterns/_bullish.cpython-37m-darwin.so
qufilab/patterns/bullish.py
qufilab/patterns/candlestick.cc
qufilab/sample/__init__.py
qufilab/sample/load_sample.py
qufilab-0.0.1.dist-info/LICENSE.MD
qufilab-0.0.1.dist-info/METADATA
qufilab-0.0.1.dist-info/WHEEL
qufilab-0.0.1.dist-info/top_level.txt
qufilab-0.0.1.dist-info/RECORD
