Metadata-Version: 2.1
Name: qufilab
Version: 0.0.1
Summary: UNKNOWN
Home-page: https://github.com/normelius/qufilab
Author: Anton Normelius
Author-email: a.normelius@gmail.com
License: UNKNOWN
Download-URL: https://github.com/normelius/qufilab/archive/v0.0.1.tar.gz
Platform: UNKNOWN
Classifier: Programming Language :: Python :: 3
Classifier: License :: OSI Approved :: MIT License
Classifier: Operating System :: OS Independent
Requires-Python: >=3.6
Requires-Dist: numpy (==1.19.1)
Requires-Dist: pandas (==1.1.0)
Requires-Dist: pybind11 (==2.5.0)
Requires-Dist: python-dateutil (==2.8.1)
Requires-Dist: pytz (==2020.1)
Requires-Dist: six (==1.15.0)
